Workbook

Sheet Chapter3

Sheet FUNCTIONS
A1: FUNCTIONS
G4: •MATHEMATICAL FUNCTIONS
G5: •TEXT FUNCTIONS
G6: •DATE AND TIME FUNCTION
G7: •LOGICAL FUNCTION
G8: •DATA VALIDATION AND FILTER

Sheet MATHEMATICAL FUNCTION
A1: MATHEMATICAL FUNCTIONS
E5: 1. SUM() | G5: 5. MIN() | I5: 9.POWER() | K5: 13.SUMIF()
E7: 2.AVERAGE() | G7: 6.COUNT() | I7: 10.SQRT() | K7: 14.COUNTIF()
E9: 3.ROUND() | G9: 7.COUNTA() | I9: 11.MAX() | K9: 15.SUMIFS()
E11: 4.ROUNDUP() | G11: 8.ROUNDDOWN() | I11: 12.PRODUCT() | K11: 16.COUNTIFS()

Sheet DESCRIPTION

Sheet SUM,AVERAGE,ROUND,MAX,MIN
A1: SUM(), AVERAGE(), ROUND(), MAX(), MIN()
B3: NO | C3: NAME | D3: ROLL NO | E3: MARK-1 | F3: MARK-2 | G3: MARK-3 | H3: TOTAL | I3: AVERAGE | J3: ROUND | K3: ROUNDUP | L3: ROUNDDOWN
B4: 1 | C4: ASKER | D4: 0000001 | E4: 56 | F4: 87 | G4: 35 | H4: =SUM(E4,F4,G4) -> 178 | I4: =AVERAGE('SUM,AVERAGE,ROUND,MAX,MIN'!E4,'SUM,AVERAGE,ROUND,MAX,MIN'!F4,'SUM,AVERAGE,ROUND,MAX,MIN'!G4) -> 59.333333 | J4: =ROUND(I4,2) -> 59.33 | K4: =ROUNDUP(I4,1) -> 59.4 | L4: =ROUNDDOWN(I4,1) -> 59.3
B5: 2 | C5: AFRATH | D5: 0000002 | E5: 98 | F5: 98 | G5: 68 | H5: =SUM(E5,F5,G5) -> 264 | I5: =AVERAGE('SUM,AVERAGE,ROUND,MAX,MIN'!E5,'SUM,AVERAGE,ROUND,MAX,MIN'!F5,'SUM,AVERAGE,ROUND,MAX,MIN'!G5) -> 88 | J5: =ROUND(I5,2) -> 88 | K5: =ROUNDUP(I5,1) -> 88 | L5: =ROUNDDOWN(I5,1) -> 88
B6: 3 | C6: NISAR | D6: 0000003 | E6: 68 | F6: 67 | G6: 97 | H6: =SUM(E6,F6,G6) -> 232 | I6: =AVERAGE('SUM,AVERAGE,ROUND,MAX,MIN'!E6,'SUM,AVERAGE,ROUND,MAX,MIN'!F6,'SUM,AVERAGE,ROUND,MAX,MIN'!G6) -> 77.333333 | J6: =ROUND(I6,2) -> 77.33 | K6: =ROUNDUP(I6,1) -> 77.4 | L6: =ROUNDDOWN(I6,1) -> 77.3
B7: 4 | C7: AMJATH | D7: 0000004 | E7: 57 | F7: 87 | G7: 58 | H7: =SUM(E7,F7,G7) -> 202 | I7: =AVERAGE('SUM,AVERAGE,ROUND,MAX,MIN'!E7,'SUM,AVERAGE,ROUND,MAX,MIN'!F7,'SUM,AVERAGE,ROUND,MAX,MIN'!G7) -> 67.333333 | J7: =ROUND(I7,2) -> 67.33 | K7: =ROUNDUP(I7,1) -> 67.4 | L7: =ROUNDDOWN(I7,1) -> 67.3
B8: 5 | C8: RAMU | D8: 0000005 | E8: 54 | F8: 47 | G8: 87 | H8: =SUM(E8,F8,G8) -> 188 | I8: =AVERAGE('SUM,AVERAGE,ROUND,MAX,MIN'!E8,'SUM,AVERAGE,ROUND,MAX,MIN'!F8,'SUM,AVERAGE,ROUND,MAX,MIN'!G8) -> 62.666667 | J8: =ROUND(I8,2) -> 62.67 | K8: =ROUNDUP(I8,1) -> 62.7 | L8: =ROUNDDOWN(I8,1) -> 62.6
B9: 6 | C9: AJESH | D9: 0000006 | E9: 24 | F9: 52 | G9: 45 | H9: =SUM(E9,F9,G9) -> 121 | I9: =AVERAGE('SUM,AVERAGE,ROUND,MAX,MIN'!E9,'SUM,AVERAGE,ROUND,MAX,MIN'!F9,'SUM,AVERAGE,ROUND,MAX,MIN'!G9) -> 40.333333 | J9: =ROUND(I9,2) -> 40.33 | K9: =ROUNDUP(I9,1) -> 40.4 | L9: =ROUNDDOWN(I9,1) -> 40.3
B10: 7 | C10: NOUFAL | D10: 0000007 | E10: 65 | F10: 25 | G10: 61 | H10: =SUM(E10,F10,G10) -> 151 | I10: =AVERAGE('SUM,AVERAGE,ROUND,MAX,MIN'!E10,'SUM,AVERAGE,ROUND,MAX,MIN'!F10,'SUM,AVERAGE,ROUND,MAX,MIN'!G10) -> 50.333333 | J10: =ROUND(I10,2) -> 50.33 | K10: =ROUNDUP(I10,1) -> 50.4 | L10: =ROUNDDOWN(I10,1) -> 50.3
B11: 8 | C11: ANVER | D11: 0000008 | E11: 54 | F11: 27 | G11: 91 | H11: =SUM(E11,F11,G11) -> 172 | I11: =AVERAGE('SUM,AVERAGE,ROUND,MAX,MIN'!E11,'SUM,AVERAGE,ROUND,MAX,MIN'!F11,'SUM,AVERAGE,ROUND,MAX,MIN'!G11) -> 57.333333 | J11: =ROUND(I11,2) -> 57.33 | K11: =ROUNDUP(I11,1) -> 57.4 | L11: =ROUNDDOWN(I11,1) -> 57.3
B12: 9 | C12: BALU | D12: 0000009 | E12: 32 | F12: 87 | G12: 93 | H12: =SUM(E12,F12,G12) -> 212 | I12: =AVERAGE('SUM,AVERAGE,ROUND,MAX,MIN'!E12,'SUM,AVERAGE,ROUND,MAX,MIN'!F12,'SUM,AVERAGE,ROUND,MAX,MIN'!G12) -> 70.666667 | J12: =ROUND(I12,2) -> 70.67 | K12: =ROUNDUP(I12,1) -> 70.7 | L12: =ROUNDDOWN(I12,1) -> 70.6
B13: 10 | C13: KARTHIK | D13: 0000010 | E13: 45 | F13: 98 | G13: 92 | H13: =SUM(E13,F13,G13) -> 235 | I13: =AVERAGE('SUM,AVERAGE,ROUND,MAX,MIN'!E13,'SUM,AVERAGE,ROUND,MAX,MIN'!F13,'SUM,AVERAGE,ROUND,MAX,MIN'!G13) -> 78.333333 | J13: =ROUND(I13,2) -> 78.33 | K13: =ROUNDUP(I13,1) -> 78.4 | L13: =ROUNDDOWN(I13,1) -> 78.3
B16: MAXIMUM | E16: =MAX(E4:E13) -> 98 | F16: =MAX(F4:F13) -> 98 | G16: =MAX(G4:G13) -> 97
B17: MINIMUM | E17: =MIN(E4:E13) -> 24 | F17: =MIN(F4:F13) -> 25 | G17: =MIN(G4:G13) -> 35
D18: LARGE | E18: =LARGE(E4:E13,2) -> 68 | F18: =LARGE(F4:F13,2) -> 98 | G18: =LARGE(G4:G13,2) -> 93
D19: SMALL | E19: =SMALL(E4:E13,2) -> 32 | F19: =SMALL(F4:F13,2) -> 27 | G19: =SMALL(G4:G13,2) -> 45

Sheet Transportation_Cost_Analysis
C1: 🚚 Transportation Cost Analysis
B3: Trip_ID | C3: Distance (km) | D3: Fuel ₹/km | E3: Toll ₹ | F3: Wage ₹ | G3: Goods ₹ | H3: Insurance % | I3: Fuel Cost ₹ | J3: Insurance ₹ | K3: Trip Cost ₹ | L3: Cost/km ₹
B4: T1 | C4: 711 | D4: 7.07 | E4: 273 | F4: 1352 | G4: 28675 | H4: 1.5 | I4: 5026.77 | J4: 430.12 | K4: 7081.9 | L4: 9.96
B5: T2 | C5: 316 | D5: 7.1 | E5: 823 | F5: 1940 | G5: 47653 | H5: 1.5 | I5: 2243.6 | J5: 714.8 | K5: 5721.4 | L5: 18.11
B6: T3 | C6: 841 | D6: 5.64 | E6: 850 | F6: 1249 | G6: 139686 | H6: 2 | I6: 4743.24 | J6: 2793.72 | K6: 9635.96 | L6: 11.46
B7: T4 | C7: 191 | D7: 5.86 | E7: 375 | F7: 1464 | G7: 143589 | H7: 1.5 | I7: 1119.26 | J7: 2153.84 | K7: 5112.1 | L7: 26.76
B8: T5 | C8: 166 | D8: 7 | E8: 746 | F8: 914 | G8: 94341 | H8: 1 | I8: 1162 | J8: 943.41 | K8: 3765.41 | L8: 22.68
B9: T6 | C9: 797 | D9: 4.99 | E9: 946 | F9: 1269 | G9: 134867 | H9: 1.5 | I9: 3977.03 | J9: 2023 | K9: 8215.04 | L9: 10.31
B10: T7 | C10: 353 | D10: 5.57 | E10: 450 | F10: 865 | G10: 114098 | H10: 1 | I10: 1966.21 | J10: 1140.98 | K10: 4422.19 | L10: 12.53
B11: T8 | C11: 911 | D11: 6.51 | E11: 367 | F11: 1446 | G11: 61245 | H11: 1 | I11: 5930.61 | J11: 612.45 | K11: 8356.06 | L11: 9.17
B12: T9 | C12: 416 | D12: 6.61 | E12: 673 | F12: 1621 | G12: 47869 | H12: 2 | I12: 2749.76 | J12: 957.38 | K12: 6001.14 | L12: 14.43
B13: T10 | C13: 201 | D13: 6.55 | E13: 588 | F13: 1348 | G13: 105909 | H13: 2 | I13: 1316.55 | J13: 2118.18 | K13: 5370.73 | L13: 26.72
N14: =SUM(K4:K13) -> 63681.93
A15: 1 | B15: What is the total Fuel Cost for all trips SUM() | K15: =SUM(I4:I13) -> 30235.03 | P15: =SUM(K4:K13) -> 63681.93
A16: 2 | B16: What is the average cost per km for all trips? AVERAGE() | K16: =AVERAGE(L4:L13) -> 16.213
A17: 3 | B17: Round the total trip cost to 1 decimal places ROUND() | K17: =ROUND(P15,1) -> 63681.9 | L17: =ROUND(SUM(K4:K13),1) -> 63681.9
A18: 4 | B18: Round up the Fuel ₹/km of a trip to the next whole number. ROUNDUP() | K18: =ROUNDUP(N18,0) -> 63 | N18: =SUM(D4:D13) -> 62.9
A19: 5 | B19: What is the minimum distance (km) covered in a trip? MIN() | K19: =MIN(C4:C13) -> 166
A20: 6 | B20: What is the maximum fuel cost among all trips? MAX() | K20: =MAX(I4:I13) -> 5930.61

Sheet DESCRIPTIONS

Sheet COUNT,COUNTA
A1: COUNT(),COUNTA(),ABSOLUTE(),SQRT(),PRODUCT(),POWER()
B3: NO | C3: NAME | D3: ROLL NO | E3: E1 | F3: E2 | G3: E3 | H3: E1-E2 | I3: ABS
B4: 1 | C4: ASKER | D4: 0000001 | E4: 56 | F4: 87 | G4: 35 | H4: =E4-F4 -> -31 | I4: =ABS(H4) -> 31 | K4: Count | L4: =COUNT(F4:F13) -> 8
B5: 2 | C5: AFRATH | D5: 0000002 | E5: 98 | F5: 98 | G5: 68 | H5: =E5-F5 -> 0 | I5: =ABS(H5) -> 0 | N5: PRODUCT | O5: =PRODUCT(4,5) -> 20
B6: 3 | C6: NISAR | D6: 0000003 | E6: 68 | F6: AB | H6: =E6-F6 -> #VALUE! | I6: =ABS(H6) -> #VALUE!
B7: 4 | C7: AMJATH | D7: 0000004 | E7: 57 | F7: 87 | G7: 58 | H7: =E7-F7 -> -30 | I7: =ABS(H7) -> 30 | K7: COUNTA | L7: =COUNTA(C4:C13) -> 10
B8: 5 | C8: RAMU | D8: 0000005 | E8: 54 | F8: 47 | G8: 87 | H8: =E8-F8 -> 7 | I8: =ABS(H8) -> 7 | N8: SQRT | O8: =SQRT(36) -> 6
B9: 6 | C9: AJESH | D9: 0000006 | E9: 24 | F9: 52 | H9: =E9-F9 -> -28 | I9: =ABS(H9) -> 28
B10: 7 | C10: NOUFAL | D10: 0000007 | E10: 65 | F10: 25 | G10: 61 | H10: =E10-F10 -> 40 | I10: =ABS(H10) -> 40 | K10: COUNTBLANK | L10: =COUNTBLANK(G4:G13) -> 3
B11: 8 | C11: ANVER | D11: 0000008 | E11: 54 | F11: AB | H11: =E11-F11 -> #VALUE! | I11: =ABS(H11) -> #VALUE! | N11: POWER | O11: =POWER(2,3) -> 8
B12: 9 | C12: BALU | D12: 0000009 | E12: 32 | F12: 87 | G12: 93 | H12: =E12-F12 -> -55 | I12: =ABS(H12) -> 55
B13: 10 | C13: KARTHIK | D13: 0000010 | E13: 45 | F13: 98 | G13: 92 | H13: =E13-F13 -> -53 | I13: =ABS(H13) -> 53
F14: Q1) Calculate the number of students?
F16: Q2) Calculate the number of students who attended the 2nd exam.
F18: Q2) Calculate the number of STUDENTS who didn’t enter the mark in E3(COUNTBLANK)

Sheet Product_Pricing&Discount_Regist
C1: 🧾Product Pricing and Discount Register
C3: Product | D3: Quantity | E3: Rate (₹) | F3: Discount %
C4: Pen | D4: 10 | E4: 15 | F4: 5
C5: Book | D5: 4 | E5: 120 | H5: How many products have discount values? | M5: =COUNTA(F4:F18) -> 9
C6: Bag | D6: 2 | E6: 450
C7: Bottle | D7: 5 | E7: 60 | F7: 12 | H7: How many products are listed | M7: =COUNTA(C4:C18) -> 15
C8: Notebook | D8: 8 | E8: 30 | F8: 8
C9: Pencil | D9: 3 | E9: 80 | F9: 5 | H9: How many products do not have a discount applied | M9: =COUNTBLANK(F4:F18) -> 6
C10: File | D10: 6 | E10: 25
C11: Scale | D11: 9 | E11: 12 | F11: 2
C12: Eraser | D12: 12 | E12: 5
C13: Marker | D13: 7 | E13: 45 | F13: 10
C14: Stapler | D14: 5 | E14: 100
C15: Tape | D15: 11 | E15: 55 | F15: 5
C16: Folder | D16: 10 | E16: 40 | F16: 3
C17: Box | D17: 4 | E17: 300
C18: Sharpener | D18: 6 | E18: 22 | F18: 7

Sheet EXCERCISE-1 
B1: 📦Dispatch Executive Data
C3: Dispatch ID | D3: Product Name | E3: Qty Dispatched | F3: Weight (kg) | G3: Dispatch Cost (₹) | H3: Packaging Charge (₹)
C4: D1 | D4: Laptop | E4: 10 | F4: 5.5378 | G4: 1200 | H4: 50 | K4: 1. What is the total Dispatch Cost for all products? | S4: =SUM(G4:G18) -> 12330
C5: D2 | D5: Monitor | E5: 5 | F5: 7.9812 | G5: 1500 | H5: 60
C6: D3 | D6: Keyboard | E6: NA | F6: 3.2456 | H6: 40 | K6: 2. What is the total Packaging Charges for all dispatches? | S6: =SUM(H4:H18) -> 604
C7: D4 | D7: Mouse | E7: 20 | F7: 1.0083 | G7: 600 | H7: 20
C8: D5 | D8: Printer | E8: 8 | F8: 6.5891 | G8: 1400 | H8: 55 | K8: 3. What is the total Quantity Dispatched? | S8: =SUM(E4:E18) -> 168
C9: D6 | D9: Scanner | E9: 6 | F9: 4.4227 | G9: 1000 | H9: 45
C10: D7 | D10: Tablet | E10: 12 | F10: 2.8745 | G10: 1100 | H10: 50 | K10: 4. What is the average Weight (kg) of the dispatched items? | S10: =AVERAGE(F4:F18) -> 3.15012
C11: D8 | D11: Router | E11: 9 | F11: 3.3451 | H11: 48
C12: D9 | D12: Speaker | E12: 14 | F12: 4.0328 | G12: 1050 | H12: 52 | K12: 5. What is the average Dispatch Cost? | S12: =AVERAGE(G4:G18) -> 948.46154
C13: D10 | D13: Hard Drive | E13: 7 | F13: 2.1197 | G13: 900 | H13: 44
C14: D11 | D14: Cable | E14: 25 | F14: 0.5176 | G14: 500 | H14: 18 | K14: 6. What is the average Packaging Charge per product? | S14: =AVERAGE(H4:H18) -> 40.266667
C15: D12 | D15: Adapter | E15: 18 | F15: 0.7149 | G15: 550 | H15: 22
C16: D13 | D16: Webcam | E16: 11 | F16: 1.2633 | G16: 650 | H16: 25 | K16: 7. How many products have Dispatch Cost? | S16: =COUNT(G4:G18) -> 13
C17: D14 | D17: Charger | E17: 13 | F17: 0.6018 | G17: 580 | H17: 20
C18: D15 | D18: Smartphone | E18: 10 | F18: 2.9974 | G18: 1300 | H18: 55 | K18: 8. How many entries have numeric values in Quantity Dispatched? | S18: =COUNT(E4:E18) -> 14
K20: 9.How many product names are listed? | S20: =COUNTA(D4:D18) -> 15
K22: 10.How many total entries are there in the Packaging Charge column? | S22: =COUNT(H4:H18) -> 15
K24: 11. What is the maximum Quantity Dispatched? | S24: =MAX(E4:E18) -> 25
I26: VLOOKU+MAX | K26: 12. Which product has the highest Dispatch Cost? | R26: =VLOOKUP(MAX(G3:G18),CHOOSE({1,2},G3:G18,D3:D18),2,FALSE) -> Monitor
K28: 13. What is the lowest Packaging Charge? | S28: =MIN(H4:H18) -> 18
I30: VLOOKU+MAX | K30: 14. Which product has the minimum Weight (kg)? | S30: =MIN(F4:F18) -> 0.5176
K32: 15. Round the Weight of the first product to 1 decimal place. | S32: =ROUND(F4,1) -> 5.5

Sheet Description_Sumif

Sheet SUMIF
C1: Inventory Stock Summary – June 2025
B3: Item ID | C3: Category | D3: Location | E3: Stock Qty | F3: Unit Cost | G3: Supplier | I3: What is the total stock quantity of Electronics items? | O3: =SUMIF(C4:C10,C4,E4:E10) -> 280
B4: INV001 | C4: Electronics | D4: Warehouse1 | E4: 120 | F4: 1500 | G4: PowerTech
B5: INV002 | C5: Furniture | D5: Warehouse2 | E5: 80 | F5: 2200 | G5: Prime Supply | I5: Find the total stock quantity in Warehouse1. | O5: =SUMIF(D4:D10,D4,E4:E10) -> 360
B6: INV003 | C6: Stationery | D6: Warehouse1 | E6: 200 | F6: 50 | G6: OfficeMart
B7: INV004 | C7: Electronics | D7: Warehouse3 | E7: 60 | F7: 1400 | G7: PowerTech | I7: Calculate the total quantity of items supplied by OfficeMart. | O7: =SUMIF(G4:G10,G9,E4:E10) -> 350
B8: INV005 | C8: Furniture | D8: Warehouse1 | E8: 40 | F8: 2100 | G8: Prime Supply
B9: INV006 | C9: Stationery | D9: Warehouse2 | E9: 150 | F9: 60 | G9: OfficeMart | I9: What is the total quantity of Furniture items? | O9: =SUMIF(C4:C10,C5,E4:E10) -> 120
B10: INV007 | C10: Electronics | D10: Warehouse2 | E10: 100 | F10: 1600 | G10: PowerTech

Sheet EXCERCISE-2
C1: 📊 Dataset: Supply Chain Order Report
C3: Order ID | D3: Region | E3: Product Category | F3: Quantity | G3: Cost per Unit | H3: Supplier | J3: 1 | K3: Find the total quantity of orders from the North region. | Q3: North | R3: =SUMIF(D3:D18,Q3,F3:F18) -> 240 | U3: =SUMIF(D4:D18,D4,F4:F18) -> 240
C4: 1001 | D4: North | E4: Electronics | F4: 50 | G4: 1200 | H4: Delta Corp | I4: >1000
C5: 1002 | D5: South | E5: Furniture | F5: 30 | G5: 800 | H5: Prime Supply | J5: 2 | K5: Find the total quantity of Furniture products ordered. | R5: =SUMIF(E3:E18,E5,F3:F18) -> 195 | U5: =SUMIF(E4:E18,E5,F4:F18) -> 195
C6: 1003 | D6: East | E6: Electronics | F6: 70 | G6: 1150 | H6: Delta Corp
C7: 1004 | D7: West | E7: Apparel | F7: 90 | G7: 450 | H7: Neo Traders | J7: 3 | K7: Calculate the total quantity of products supplied by Delta Corp. | R7: =SUMIF(H3:H18,H4,F3:F18) -> 320 | U7: =SUMIF(H4:H18,H4,F4:F18) -> 320
C8: 1005 | D8: North | E8: Furniture | F8: 40 | G8: 850 | H8: Prime Supply
C9: 1006 | D9: East | E9: Electronics | F9: 65 | G9: 1250 | H9: Delta Corp | J9: 4 | K9: What is the total quantity of Apparel ordered across all regions? | R9: =SUMIF(E3:E18,E7,F3:F18) -> 320 | U9: =SUMIF(E4:E18,E7,F4:F18) -> 320
C10: 1007 | D10: South | E10: Apparel | F10: 100 | G10: 420 | H10: Neo Traders
C11: 1008 | D11: West | E11: Furniture | F11: 25 | G11: 780 | H11: Prime Supply | J11: 5 | K11: Calculate the total number of products ordered in the East region. | R11: =SUMIF(D3:D18,D6,F3:F18) -> 190 | U11: =SUMIF(D4:D18,D6,F4:F18) -> 190
C12: 1009 | D12: North | E12: Electronics | F12: 80 | G12: 1100 | H12: Delta Corp
C13: 1010 | D13: South | E13: Apparel | F13: 60 | G13: 500 | H13: Neo Traders | J13: 6 | K13: Find the total quantity of Furniture supplied by Prime Supply.
C14: 1011 | D14: East | E14: Furniture | F14: 35 | G14: 870 | H14: Prime Supply
C15: 1012 | D15: West | E15: Electronics | F15: 55 | G15: 1180 | H15: Delta Corp | J15: 7 | K15: What is the total quantity ordered from the South region by Neo Traders?
C16: 1013 | D16: South | E16: Furniture | F16: 45 | G16: 820 | H16: Prime Supply
C17: 1014 | D17: North | E17: Apparel | F17: 70 | G17: 470 | H17: Neo Traders | J17: 8 | K17: Find the quantity of Electronics ordered in the West region.
C18: 1015 | D18: East | E18: Furniture | F18: 20 | G18: 860 | H18: Prime Supply
J19: 9 | K19: Calculate the total quantity of all products supplied by Neo Traders. | R19: =SUMIF(H3:H18,H7,F3:F18) -> 320 | U19: =SUMIF(H4:H18,H7,F4:F18) -> 320
J21: 10 | K21: How many units of Electronics were supplied overall? | R21: =SUMIF(E3:E18,E4,F3:F18) -> 320 | U21: =SUMIF(E4:E18,E4,F4:F18) -> 320
J23: 11 | K23: Sum the quantity of Furniture products ordered in the South region.
J25: 12 | K25: What is the quantity of Apparel ordered in each region? | R25: =SUMIF(E3:E18,E17,F3:F18) -> 320 | U25: =SUMIF(E4:E18,E7,F4:F18) -> 320
J27: 13 | K27: Find the total quantity of all orders where Cost per Unit is more than ₹1000. | S27: =SUMIF(G3:G18,">1000",F3:F18) -> 320 | U27: =SUMIF(G4:G18,I4,F4:F18) -> 320
J29: 14 | K29: Find the total quantity of Electronics supplied by Delta Corp.
J31: 15 | K31: What is the total quantity ordered across all regions? | U31: =SUM(F4:F18) -> 835

Sheet Description_Sumifs

Sheet SUMIFS
C1: Inventory Stock Summary – June 2025
B3: Item ID | C3: Category | D3: Location | E3: Stock Qty | F3: Unit Cost | G3: Supplier | I3: 1 | J3: What is the total stock quantity of "Electronics" items located in "Warehouse2"? | S3: =SUMIFS(E4:E10,C4:C10,C4,D4:D10,D5) -> 100
B4: INV001 | C4: Electronics | D4: Warehouse1 | E4: 120 | F4: 1500 | G4: PowerTech | H4: <100
B5: INV002 | C5: Furniture | D5: Warehouse2 | E5: 80 | F5: 2200 | G5: Prime Supply | I5: 2 | J5: Calculate the total stock quantity supplied by "PowerTech" from "Warehouse1". | S5: =SUMIFS(E4:E10,G4:G10,G4,D4:D10,D4) -> 120
B6: INV003 | C6: Stationery | D6: Warehouse1 | E6: 200 | F6: 50 | G6: OfficeMart
B7: INV004 | C7: Electronics | D7: Warehouse3 | E7: 60 | F7: 1400 | G7: PowerTech | I7: 3 | J7: Find the total stock quantity of items in "Warehouse2" that belong to the "Furniture" category. | T7: =SUMIFS(E4:E10,C4:C10,C5,D4:D10,D5) -> 80
B8: INV005 | C8: Furniture | D8: Warehouse1 | E8: 40 | F8: 2100 | G8: Prime Supply
B9: INV006 | C9: Stationery | D9: Warehouse2 | E9: 150 | F9: 60 | G9: OfficeMart | I9: 4 | J9: What is the total stock quantity of items supplied by "OfficeMart" and located in "Warehouse2"? | T9: =SUMIFS(E4:E10,G4:G10,G6,D4:D10,D5) -> 150
B10: INV007 | C10: Electronics | D10: Warehouse2 | E10: 100 | F10: 1600 | G10: PowerTech
I11: 5 | J11: Find the total quantity of "Stationery" items with a unit cost less than 100. | T11: =SUMIFS(E4:E10,C4:C10,C6,F4:F10,H4) -> 350

Sheet EXCERCISE-3
C1: 📊 Dataset: Supply Chain Order Report
C3: Order ID | D3: Region | E3: Product Category | F3: Quantity | G3: Cost per Unit | H3: Supplier | J3: 1 | K3: What is the total quantity of Electronics ordered from the East region?
C4: 1001 | D4: North | E4: Electronics | F4: 50 | G4: 1200 | H4: Delta Corp | I4: >1000 | Q4: =SUMIFS(F4:F18,E4:E18,E4,D4:D18,D6) -> 135
C5: 1002 | D5: South | E5: Furniture | F5: 30 | G5: 800 | H5: Prime Supply | J5: 2 | K5: Find the total quantity of Apparel supplied by Neo Traders. | Q5: =SUMIFS(F4:F18,E4:E18,E7,H4:H18,H7) -> 320
C6: 1003 | D6: East | E6: Electronics | F6: 70 | G6: 1150 | H6: Delta Corp | I6: <>west
C7: 1004 | D7: West | E7: Apparel | F7: 90 | G7: 450 | H7: Neo Traders | J7: 3 | K7: Calculate the total quantity of Furniture orders from the South region. | R7: =SUMIFS(F4:F18,E4:E18,E5,D4:D18,D5) -> 75
C8: 1005 | D8: North | E8: Furniture | F8: 40 | G8: 850 | H8: Prime Supply | I8: <>prime supply
C9: 1006 | D9: East | E9: Electronics | F9: 65 | G9: 1250 | H9: Delta Corp | J9: 4 | K9: What is the total quantity of products with a Cost per Unit greater than ₹1000 and supplied by Delta Corp? | U9: =SUMIFS(F4:F18,H4:H18,H4,G4:G18,I4) -> 320
C10: 1007 | D10: South | E10: Apparel | F10: 100 | G10: 420 | H10: Neo Traders | I10: >1000
C11: 1008 | D11: West | E11: Furniture | F11: 25 | G11: 780 | H11: Prime Supply | J11: 5 | K11: Find the total quantity of Electronics ordered from all regions except West. | U11: =SUMIFS(F4:F18,E4:E18,E4,D4:D18,I6) -> 265
C12: 1009 | D12: North | E12: Electronics | F12: 80 | G12: 1100 | H12: Delta Corp | I12: <500
C13: 1010 | D13: South | E13: Apparel | F13: 60 | G13: 500 | H13: Neo Traders | J13: 6 | K13: What is the total quantity of orders from the North region for suppliers other than Prime Supply? | U13: =SUMIFS(F4:F18,D4:D18,D4,H4:H18,I8) -> 200
C14: 1011 | D14: East | E14: Furniture | F14: 35 | G14: 870 | H14: Prime Supply
C15: 1012 | D15: West | E15: Electronics | F15: 55 | G15: 1180 | H15: Delta Corp | J15: 7 | K15: Calculate the total quantity of all products in the East region that cost more than ₹1000 per unit. | U15: =SUMIFS(F4:F18,D4:D18,D6,G4:G18,I10) -> 135
C16: 1013 | D16: South | E16: Furniture | F16: 45 | G16: 820 | H16: Prime Supply
C17: 1014 | D17: North | E17: Apparel | F17: 70 | G17: 470 | H17: Neo Traders | J17: 8 | K17: Find the total quantity of Furniture supplied by Prime Supply in West and South regions. | S17: =SUMIFS(F4:F18,E4:E18,E5,H4:H18,H5,D4:D18,D7)+SUMIFS(F4:F18,E4:E18,E5,H4:H18,H5,D4:D18,D10) -> 100
C18: 1015 | D18: East | E18: Furniture | F18: 20 | G18: 860 | H18: Prime Supply
J19: 9 | K19: What is the total quantity of Apparel with a cost per unit less than ₹500? | S19: =SUMIFS(F4:F18,E4:E18,E10,G4:G18,I12) -> 260
J21: 10 | K21: Find the quantity of Electronics products supplied by Delta Corp from the North and East regions. | U21: =SUMIFS(F4:F18,E4:E18,E4,H4:H18,H4,D4:D18,D8)+SUMIFS(F4:F18,E4:E18,E4,H4:H18,H4,D4:D18,D9) -> 265

Sheet Description_Countif

Sheet Description_Countifs

Sheet COUNTIF&COUNTIFS
B1: 📋 Procurement Requests | E1: A Procurement Request is a formal request made by a department or employee within an organization to purchase goods or services.
B3: Request ID | C3: Department | D3: Item Category | E3: Status | F3: Supplier | H3: ✅ COUNTIF:
B4: PR001 | C4: IT | D4: Electronics | E4: Approved | F4: TechMart | G4: approved | H4: 1. How many procurement requests are in "Approved" status? | P4: =COUNTIF(E4:E13,G4) -> 6
B5: PR002 | C5: HR | D5: Stationery | E5: Pending | F5: OfficeNeeds | H5: 👉 (Count how many times "Approved" appears in the Status column)
B6: PR003 | C6: Finance | D6: Furniture | E6: Approved | F6: Prime Supply | H6: 2. How many requests were submitted by the "HR" department? | P6: =COUNTIF(C4:C13,C5) -> 3
B7: PR004 | C7: IT | D7: Electronics | E7: Rejected | F7: TechMart | H7: 3. How many requests were made for the item category "Electronics"? | P7: =COUNTIF(D4:D13,D4) -> 4
B8: PR005 | C8: HR | D8: Stationery | E8: Approved | F8: OfficeNeeds
B9: PR006 | C9: Admin | D9: Furniture | E9: Pending | F9: Prime Supply | H9: ✅ COUNTIFS:
B10: PR007 | C10: IT | D10: Furniture | E10: Approved | F10: FurniDepot | H10: 4. How many approved requests came from the "IT" department? | P10: =COUNTIFS(C4:C13,C4,E4:E13,E6) -> 2
B11: PR008 | C11: Finance | D11: Electronics | E11: Approved | F11: TechMart | H11: 👉 (Count where Department is IT and Status is Approved)
B12: PR009 | C12: Admin | D12: Stationery | E12: Rejected | F12: OfficeNeeds | H12: 5. How many requests for "Stationery" items were supplied by "OfficeNeeds"? | P12: =COUNTIFS(D4:D13,D5,F4:F13,F5) -> 3
B13: PR010 | C13: HR | D13: Electronics | E13: Approved | F13: TechMart
E14: =COUNTA(E4:E13) -> 10

Sheet EXCERCISE-4
B1: Fleet Operations Log – June 2025 | H1: Fleet Management is the process of organizing and coordinating vehicles used by a business or organization.
B3: Vehicle ID | C3: Type | D3: Location | E3: Status | F3: Fuel Type | G3: Service Due | H3: Driver | J3: ✅ COUNTIF Questions (Single Condition): | Q3: ✅ COUNTIFS Questions (Multiple Conditions):
B4: FL001 | C4: Truck | D4: Depot A | E4: Active | F4: Diesel | G4: Yes | H4: Ramesh
B5: FL002 | C5: Van | D5: Depot B | E5: In Repair | F5: Petrol | G5: No | H5: Suresh | J5: 1. How many vehicles are currently marked as "Active"? | P5: =COUNTIF(E4:E13,E4) -> 6 | Q5: 9. How many "Active" trucks are located in "Depot A"?
B6: FL003 | C6: Car | D6: Depot A | E6: Active | F6: Petrol | G6: No | H6: Anita | V6: =COUNTIFS(E4:E13,E4,C4:C13,C4,D4:D13,D4) -> 3
B7: FL004 | C7: Truck | D7: Depot C | E7: Active | F7: Diesel | G7: Yes | H7: Ramesh | J7: 2. How many vehicles are located in "Depot A"? | P7: =COUNTIF(D4:D13,D4) -> 4 | Q7: 10. Count how many vehicles of type "Car" are in "Depot C" and marked as "In Repair".
B8: FL005 | C8: Van | D8: Depot B | E8: Retired | F8: CNG | G8: No | H8: Jaya | V8: =COUNTIFS(C4:C13,C6,D4:D13,D7,E4:E13,E5) -> 1
B9: FL006 | C9: Truck | D9: Depot A | E9: Active | F9: Diesel | G9: Yes | H9: Ramesh | J9: 3. Count how many vehicles are of type "Truck". | P9: =COUNTIF(C4:C13,C4) -> 4 | Q9: 11. How many vehicles driven by "Ramesh" are due for service?
B10: FL007 | C10: Car | D10: Depot C | E10: In Repair | F10: Petrol | G10: Yes | H10: Anita | V10: =COUNTIFS(H4:H13,H4,G4:G13,G4) -> 3
B11: FL008 | C11: Van | D11: Depot B | E11: Active | F11: Diesel | G11: No | H11: Suresh | J11: 4. How many vehicles are due for service ("Yes")? | P11: =COUNTIF(G4:G13,G4) -> 5 | Q11: 12. How many "Diesel" vehicles are located in "Depot B"? | W11: =COUNTIFS(F4:F13,F4,D4:D13,D5) -> 1
B12: FL009 | C12: Truck | D12: Depot A | E12: Active | F12: Diesel | G12: No | H12: Ramesh
B13: FL010 | C13: Car | D13: Depot C | E13: Retired | F13: CNG | G13: Yes | H13: Jaya | J13: 5. Count how many vehicles use "Diesel" as fuel. | P13: =COUNTIF(F4:F13,F4) -> 5 | Q13: 13. How many "Petrol" vehicles are "Active"? | W13: =COUNTIFS(F4:F13,F5,E4:E13,E4) -> 1
J15: 6. How many drivers are assigned to "Ramesh"? | P15: =COUNTIF(H4:H13,H4) -> 4 | Q15: 14. How many vehicles in "Depot A" are not due for service? | W15: =COUNTIFS(D4:D13,D4,G4:G13,G5) -> 2
J17: 7. How many vehicles are in the "Retired" status? | P17: =COUNTIF(E4:E13,E8) -> 2 | Q17: 15. Count how many "Vans" are in "Depot B" and have the status "Active". | Y17: =COUNTIFS(C4:C13,C5,D4:D13,D5,E4:E13,E4) -> 1
J19: 8. Count how many vehicles are of type "Van". | P19: =COUNTIF(C4:C13,C8) -> 3
